pychemparse/__init__.py
pychemparse/data.py
pychemparse/default.css
pychemparse/default.js
pychemparse/elements.py
pychemparse/file.py
pychemparse/gpaw_elements.py
pychemparse/gpaw_regex.json
pychemparse/logging_config.py
pychemparse/orca_elements.py
pychemparse/orca_regex.json
pychemparse/regex_request.py
pychemparse/regex_settings.py
pychemparse/scripts.py
pychemparse/units_and_constants.py
pychemparse/vasp_elements.py
pychemparse/vasp_regex.json
pychemparse-0.6.1.dist-info/LICENSE
pychemparse-0.6.1.dist-info/METADATA
pychemparse-0.6.1.dist-info/WHEEL
pychemparse-0.6.1.dist-info/entry_points.txt
pychemparse-0.6.1.dist-info/RECORD
