Metadata-Version: 2.1
Name: pychemparse
Version: 0.6.1
Summary: A package for extracting data from ORCA .out, GPAW .txt files, and more. It allows for the creation of user-defined extraction patterns to ensure accurate data extraction from various ORCA versions.
Author: ivan
Author-email: imtambovtcev@gmail.com
Requires-Python: >=3.10,<4.0
Classifier: Programming Language :: Python :: 3
Classifier: Programming Language :: Python :: 3.10
Classifier: Programming Language :: Python :: 3.11
Requires-Dist: bitmath (>=1.3.3.1,<2.0.0.0)
Requires-Dist: numpy (>=1.26.4,<2.0.0)
Requires-Dist: openpyxl (>=3.1.2,<4.0.0)
Requires-Dist: pandas (>=2.2.1,<3.0.0)
Requires-Dist: pint (>=0.23,<0.24)
Requires-Dist: tqdm (>=4.66.2,<5.0.0)
